{
    "ScaleFactor_egammaEff_WP80" : {
        "pt_eta_ratio" : {
            "pt:[10.0,20.0]": {
                "eta:[-2.5,-2.0]": {
                    "value": 0.837,
                    "error": 0.024
                },
                "eta:[-2.0,-1.566]": {
                    "value": 0.8,
                    "error": 0.014
                },
                "eta:[-1.566,-1.444]": {
                    "value": 0.952,
                    "error": 0.078
                },
                "eta:[-1.444,-0.8]": {
                    "value": 0.915,
                    "error": 0.035
                },
                "eta:[-0.8,0.0]": {
                    "value": 0.903,
                    "error": 0.027
                },
                "eta:[0.0,0.8]": {
                    "value": 0.928,
                    "error": 0.027
                },
                "eta:[0.8,1.444]": {
                    "value": 0.937,
                    "error": 0.035
                },
                "eta:[1.444,1.566]": {
                    "value": 0.968,
                    "error": 0.077
                },
                "eta:[1.566,2.0]": {
                    "value": 0.843,
                    "error": 0.014
                },
                "eta:[2.0,2.5]": {
                    "value": 0.851,
                    "error": 0.024
                }
            },
            "pt:[20.0,30.0]": {
                "eta:[-2.5,-2.0]": {
                    "value": 0.863,
                    "error": 0.013
                },
                "eta:[-2.0,-1.566]": {
                    "value": 0.871,
                    "error": 0.013
                },
                "eta:[-1.566,-1.444]": {
                    "value": 0.891,
                    "error": 0.052
                },
                "eta:[-1.444,-0.8]": {
                    "value": 0.923,
                    "error": 0.021
                },
                "eta:[-0.8,0.0]": {
                    "value": 0.92,
                    "error": 0.017
                },
                "eta:[0.0,0.8]": {
                    "value": 0.945,
                    "error": 0.017
                },
                "eta:[0.8,1.444]": {
                    "value": 0.919,
                    "error": 0.021
                },
                "eta:[1.444,1.566]": {
                    "value": 0.865,
                    "error": 0.052
                },
                "eta:[1.566,2.0]": {
                    "value": 0.866,
                    "error": 0.013
                },
                "eta:[2.0,2.5]": {
                    "value": 0.892,
                    "error": 0.013
                }
            },
            "pt:[30.0,40.0]": {
                "eta:[-2.5,-2.0]": {
                    "value": 0.915,
                    "error": 0.008
                },
                "eta:[-2.0,-1.566]": {
                    "value": 0.916,
                    "error": 0.005
                },
                "eta:[-1.566,-1.444]": {
                    "value": 0.92,
                    "error": 0.012
                },
                "eta:[-1.444,-0.8]": {
                    "value": 0.949,
                    "error": 0.008
                },
                "eta:[-0.8,0.0]": {
                    "value": 0.941,
                    "error": 0.004
                },
                "eta:[0.0,0.8]": {
                    "value": 0.961,
                    "error": 0.004
                },
                "eta:[0.8,1.444]": {
                    "value": 0.945,
                    "error": 0.008
                },
                "eta:[1.444,1.566]": {
                    "value": 0.918,
                    "error": 0.012
                },
                "eta:[1.566,2.0]": {
                    "value": 0.919,
                    "error": 0.005
                },
                "eta:[2.0,2.5]": {
                    "value": 0.927,
                    "error": 0.008
                }
            },
            "pt:[40.0,50.0]": {
                "eta:[-2.5,-2.0]": {
                    "value": 0.93,
                    "error": 0.006
                },
                "eta:[-2.0,-1.566]": {
                    "value": 0.939,
                    "error": 0.003
                },
                "eta:[-1.566,-1.444]": {
                    "value": 0.953,
                    "error": 0.008
                },
                "eta:[-1.444,-0.8]": {
                    "value": 0.956,
                    "error": 0.005
                },
                "eta:[-0.8,0.0]": {
                    "value": 0.951,
                    "error": 0.004
                },
                "eta:[0.0,0.8]": {
                    "value": 0.965,
                    "error": 0.004
                },
                "eta:[0.8,1.444]": {
                    "value": 0.954,
                    "error": 0.005
                },
                "eta:[1.444,1.566]": {
                    "value": 0.932,
                    "error": 0.007
                },
                "eta:[1.566,2.0]": {
                    "value": 0.943,
                    "error": 0.003
                },
                "eta:[2.0,2.5]": {
                    "value": 0.943,
                    "error": 0.006
                }
            },
            "pt:[50.0,200.0]": {
                "eta:[-2.5,-2.0]": {
                    "value": 0.936,
                    "error": 0.007
                },
                "eta:[-2.0,-1.566]": {
                    "value": 0.95,
                    "error": 0.004
                },
                "eta:[-1.566,-1.444]": {
                    "value": 0.965,
                    "error": 0.008
                },
                "eta:[-1.444,-0.8]": {
                    "value": 0.957,
                    "error": 0.004
                },
                "eta:[-0.8,0.0]": {
                    "value": 0.957,
                    "error": 0.007
                },
                "eta:[0.0,0.8]": {
                    "value": 0.971,
                    "error": 0.007
                },
                "eta:[0.8,1.444]": {
                    "value": 0.964,
                    "error": 0.004
                },
                "eta:[1.444,1.566]": {
                    "value": 0.944,
                    "error": 0.008
                },
                "eta:[1.566,2.0]": {
                    "value": 0.958,
                    "error": 0.004
                },
                "eta:[2.0,2.5]": {
                    "value": 0.954,
                    "error": 0.006
                }
            }
        }
    }
}
